[
  {
    "num1": 4.0,
    "num2": 3.0,
    "operator": "**",
    "result": 64.0
  },
  {
    "num1": 1265.0,
    "num2": 854.0,
    "operator": "*",
    "result": 1080310.0
  },
  {
    "num1": 1.0,
    "num2": 2.0,
    "operator": "-",
    "result": -1.0
  },
  {
    "num1": 7.0,
    "num2": 4.0,
    "operator": "*",
    "result": 28.0
  },
  {
    "num1": 7.0,
    "num2": 4.0,
    "operator": "*",
    "result": 28.0
  },
  {
    "num1": 15.0,
    "num2": 8.0,
    "operator": "/",
    "result": 1.875
  },
  {
    "num1": 15.0,
    "num2": 8.0,
    "operator": "/",
    "result": 1.875
  }
]